doframework/__init__.py
doframework/api.py
doframework/core/__init__.py
doframework/core/gp.py
doframework/core/hit_and_run.py
doframework/core/inputs.py
doframework/core/metrics.py
doframework/core/optimizer.py
doframework/core/poi.py
doframework/core/pwl.py
doframework/core/sampler.py
doframework/core/storage.py
doframework/core/triangulation.py
doframework/core/utils.py
doframework/flow/__init__.py
doframework/flow/datasets.py
doframework/flow/metrics.py
doframework/flow/mock.py
doframework/flow/objectives.py
doframework/flow/solutions.py
doframework-0.2.1.data/scripts/doframework-setup.sh
doframework-0.2.1.dist-info/AUTHORS
doframework-0.2.1.dist-info/LICENSE
doframework-0.2.1.dist-info/METADATA
doframework-0.2.1.dist-info/WHEEL
doframework-0.2.1.dist-info/top_level.txt
doframework-0.2.1.dist-info/RECORD
