Metadata-Version: 2.1
Name: doframework
Version: 0.2.1
Summary: A testing framework for decision optimization model learning algorithms.
Home-page: https://github.com/IBM/doframework
Author: Orit Davidovich
Author-email: orit.davidovich@ibm.com
License: Apache-2.0
Platform: UNKNOWN
Classifier: Programming Language :: Python :: 3
Classifier: Programming Language :: Python :: 3 :: Only
Classifier: License :: OSI Approved :: Apache Software License
Classifier: Operating System :: OS Independent
Requires-Python: >=3.8
Requires-Dist: numpy
Requires-Dist: pandas
Requires-Dist: matplotlib
Requires-Dist: ray[default,k8s,serve] (>=1.13.0)
Requires-Dist: rayvens (>=0.7.0)
Requires-Dist: ibm-cos-sdk (>=2.10.0)
Requires-Dist: boto3 (>=1.17.110)
Requires-Dist: aiohttp (>=3.7.4)
Requires-Dist: aioredis (>=1.3.1)
Requires-Dist: scikit-learn (>=0.24.1)
Requires-Dist: scipy
Requires-Dist: PuLP (>=2.4)
Requires-Dist: GPy (>=1.9.9)
